{
  "data": [
    {
      "interval": {
        "from": "2024-06-12T00:00:00Z",
        "to": "2024-06-13T00:00:00Z"
      },
      "outputs": {
        "data": {
          "bands": {
            "B0": {
              "stats": {
                "min": 0.08469539135694504,
                "max": 0.5511363744735718,
                "mean": 0.20345637911894723,
                "stDev": 0.09933101393934528,
                "sampleCount": 316293,
                "noDataCount": 153784
              }
            },
            "B1": {
              "stats": {
                "min": 0.14000000059604645,
                "max": 0.32760000228881836,
                "mean": 0.1920983267610493,
                "stDev": 0.053207442963372716,
                "sampleCount": 316293,
                "noDataCount": 153784
              }
            },
            "B2": {
              "stats": {
                "min": 0.09480000287294388,
                "max": 0.17219999432563782,
                "mean": 0.1233856144853017,
                "stDev": 0.017982047044867902,
                "sampleCount": 316293,
                "noDataCount": 153784
              }
            }
          }
        },
        "scl": {
          "bands": {
            "B0": {
              "stats": {
                "min": 5.0,
                "max": 5.0,
                "mean": 5.0,
                "stDev": 0.0,
                "sampleCount": 316293,
                "noDataCount": 153784
              }
            }
          }
        }
      }
    },
    {
      "interval": {
        "from": "2024-06-17T00:00:00Z",
        "to": "2024-06-18T00:00:00Z"
      },
      "outputs": {
        "data": {
          "bands": {
            "B0": {
              "stats": {
                "min": 0.1487710177898407,
                "max": 0.46786248683929443,
                "mean": 0.22886414744326591,
                "stDev": 0.05995725492902356,
                "sampleCount": 316293,
                "noDataCount": 153784
              }
            },
            "B1": {
              "stats": {
                "min": 0.24740000069141388,
                "max": 0.3928000032901764,
                "mean": 0.30788426243765327,
                "stDev": 0.03547929187377495,
                "sampleCount": 316293,
                "noDataCount": 153784
              }
            },
            "B2": {
              "stats": {
                "min": 0.13819999992847443,
                "max": 0.22380000352859497,
                "mean": 0.19215176975755668,
                "stDev": 0.015155577099019962,
                "sampleCount": 316293,
                "noDataCount": 153784
              }
            }
          }
        },
        "scl": {
          "bands": {
            "B0": {
              "stats": {
                "min": 5.0,
                "max": 5.0,
                "mean": 5.0,
                "stDev": 0.0,
                "sampleCount": 316293,
                "noDataCount": 153784
              }
            }
          }
        }
      }
    },
    {
      "interval": {
        "from": "2024-06-22T00:00:00Z",
        "to": "2024-06-23T00:00:00Z"
      },
      "outputs": {
        "data": {
          "bands": {
            "B0": {
              "stats": {
                "min": 0.13002733886241913,
                "max": 0.642702579498291,
                "mean": 0.26540948454939556,
                "stDev": 0.10693195055790272,
                "sampleCount": 316293,
                "noDataCount": 153784
              }
            },
            "B1": {
              "stats": {
                "min": 0.14429999887943268,
                "max": 0.4099999964237213,
                "mean": 0.2104000161725126,
                "stDev": 0.06698109477682117,
                "sampleCount": 316293,
                "noDataCount": 153784
              }
            },
            "B2": {
              "stats": {
                "min": 0.07429999858140945,
                "max": 0.17820000648498535,
                "mean": 0.1175292831196153,
                "stDev": 0.020895114019962847,
                "sampleCount": 316293,
                "noDataCount": 153784
              }
            }
          }
        },
        "scl": {
          "bands": {
            "B0": {
              "stats": {
                "min": 4.0,
                "max": 5.0,
                "mean": 4.978678103982016,
                "stDev": 0.14445508910475643,
                "sampleCount": 316293,
                "noDataCount": 153784
              }
            }
          }
        }
      }
    },
    {
      "interval": {
        "from": "2024-06-27T00:00:00Z",
        "to": "2024-06-28T00:00:00Z"
      },
      "outputs": {
        "data": {
          "bands": {
            "B0": {
              "stats": {
                "min": -0.02063789777457714,
                "max": -0.005215742159634829,
                "mean": -0.011873014082592458,
                "stDev": 0.0029422574447708783,
                "sampleCount": 316293,
                "noDataCount": 153784
              }
            },
            "B1": {
              "stats": {
                "min": 0.8271999955177307,
                "max": 0.8952000141143799,
                "mean": 0.851088096059502,
                "stDev": 0.016434674259112103,
                "sampleCount": 316293,
                "noDataCount": 153784
              }
            },
            "B2": {
              "stats": {
                "min": 0.8479999899864197,
                "max": 0.9120000004768372,
                "mean": 0.8715169041108398,
                "stDev": 0.015497419036739382,
                "sampleCount": 316293,
                "noDataCount": 153784
              }
            }
          }
        },
        "scl": {
          "bands": {
            "B0": {
              "stats": {
                "min": 9.0,
                "max": 9.0,
                "mean": 9.0,
                "stDev": 0.0,
                "sampleCount": 316293,
                "noDataCount": 153784
              }
            }
          }
        }
      }
    },
    {
      "interval": {
        "from": "2024-07-02T00:00:00Z",
        "to": "2024-07-03T00:00:00Z"
      },
      "outputs": {
        "data": {
          "bands": {
            "B0": {
              "stats": {
                "min": 0.14445063471794128,
                "max": 0.6554364562034607,
                "mean": 0.3180844272337463,
                "stDev": 0.11255125559978706,
                "sampleCount": 316293,
                "noDataCount": 153784
              }
            },
            "B1": {
              "stats": {
                "min": 0.20520000159740448,
                "max": 0.4415999948978424,
                "mean": 0.27122266124265054,
                "stDev": 0.04034285165440653,
                "sampleCount": 316293,
                "noDataCount": 153784
              }
            },
            "B2": {
              "stats": {
                "min": 0.0828000009059906,
                "max": 0.1940000057220459,
                "mean": 0.13877861159382157,
                "stDev": 0.020342923473111993,
                "sampleCount": 316293,
                "noDataCount": 153784
              }
            }
          }
        },
        "scl": {
          "bands": {
            "B0": {
              "stats": {
                "min": 5.0,
                "max": 8.0,
                "mean": 5.056784547317334,
                "stDev": 0.4088143308864086,
                "sampleCount": 316293,
                "noDataCount": 153784
              }
            }
          }
        }
      }
    },
    {
      "interval": {
        "from": "2024-07-07T00:00:00Z",
        "to": "2024-07-08T00:00:00Z"
      },
      "outputs": {
        "data": {
          "bands": {
            "B0": {
              "stats": {
                "min": -0.03491401672363281,
                "max": -0.00957178883254528,
                "mean": -0.019551675157397617,
                "stDev": 0.00463436974856757,
                "sampleCount": 316293,
                "noDataCount": 153784
              }
            },
            "B1": {
              "stats": {
                "min": 0.7408000230789185,
                "max": 0.8104000091552734,
                "mean": 0.7813844744748408,
                "stDev": 0.014490713977460792,
                "sampleCount": 316293,
                "noDataCount": 153784
              }
            },
            "B2": {
              "stats": {
                "min": 0.7896000146865845,
                "max": 0.8352000117301941,
                "mean": 0.8124848849979864,
                "stDev": 0.011095757243504022,
                "sampleCount": 316293,
                "noDataCount": 153784
              }
            }
          }
        },
        "scl": {
          "bands": {
            "B0": {
              "stats": {
                "min": 9.0,
                "max": 9.0,
                "mean": 9.0,
                "stDev": 0.0,
                "sampleCount": 316293,
                "noDataCount": 153784
              }
            }
          }
        }
      }
    },
    {
      "interval": {
        "from": "2024-07-12T00:00:00Z",
        "to": "2024-07-13T00:00:00Z"
      },
      "outputs": {
        "data": {
          "bands": {
            "B0": {
              "stats": {
                "min": 0.03487592190504074,
                "max": 0.04835982248187065,
                "mean": 0.04089727268059944,
                "stDev": 0.0025497731347164138,
                "sampleCount": 316293,
                "noDataCount": 153784
              }
            },
            "B1": {
              "stats": {
                "min": 0.5971999764442444,
                "max": 0.6255999803543091,
                "mean": 0.6124140179772297,
                "stDev": 0.006179718605691621,
                "sampleCount": 316293,
                "noDataCount": 153784
              }
            },
            "B2": {
              "stats": {
                "min": 0.5479999780654907,
                "max": 0.5771999955177307,
                "mean": 0.5642873479998952,
                "stDev": 0.005461277856355338,
                "sampleCount": 316293,
                "noDataCount": 153784
              }
            }
          }
        },
        "scl": {
          "bands": {
            "B0": {
              "stats": {
                "min": 9.0,
                "max": 9.0,
                "mean": 9.0,
                "stDev": 0.0,
                "sampleCount": 316293,
                "noDataCount": 153784
              }
            }
          }
        }
      }
    }
  ],
  "status": "OK"
}
